{
  "main": {
    "id": "6cca941706e90485",
    "type": "split",
    "children": [
      {
        "id": "4c0d25f1989c69c1",
        "type": "tabs",
        "children": [
          {
            "id": "4d53f795367e7826",
            "type": "leaf",
            "state": {
              "type": "markdown",
              "state": {
                "file": "Self_Academics/Algorithms/Ch12_Binary_Search_Trees.md",
                "mode": "source",
                "source": false
              },
              "icon": "lucide-file",
              "title": "Ch12_Binary_Search_Trees"
            }
          }
        ]
      }
    ],
    "direction": "vertical"
  },
  "left": {
    "id": "e0da0efacb5f591b",
    "type": "split",
    "children": [
      {
        "id": "a71a389afc5cb631",
        "type": "tabs",
        "children": [
          {
            "id": "d0ca922b8cb2f2c5",
            "type": "leaf",
            "state": {
              "type": "file-explorer",
              "state": {
                "sortOrder": "alphabetical",
                "autoReveal": false
              },
              "icon": "lucide-folder-closed",
              "title": "Files"
            }
          },
          {
            "id": "fa9070d58709a2a4",
            "type": "leaf",
            "state": {
              "type": "search",
              "state": {
                "query": "",
                "matchingCase": false,
                "explainSearch": false,
                "collapseAll": false,
                "extraContext": false,
                "sortOrder": "alphabetical"
              },
              "icon": "lucide-search",
              "title": "Search"
            }
          },
          {
            "id": "3274ae617db910cd",
            "type": "leaf",
            "state": {
              "type": "bookmarks",
              "state": {},
              "icon": "lucide-bookmark",
              "title": "Bookmarks"
            }
          }
        ]
      }
    ],
    "direction": "horizontal",
    "width": 338.5
  },
  "right": {
    "id": "21143ca00769d09e",
    "type": "split",
    "children": [
      {
        "id": "2545c120e4ad72f1",
        "type": "tabs",
        "children": [
          {
            "id": "d262f2297003ff66",
            "type": "leaf",
            "state": {
              "type": "backlink",
              "state": {
                "file": "HUST_Academics/Software Engineering/Chapter6_Comprehensive.md",
                "collapseAll": false,
                "extraContext": false,
                "sortOrder": "alphabetical",
                "showSearch": false,
                "searchQuery": "",
                "backlinkCollapsed": false,
                "unlinkedCollapsed": true
              },
              "icon": "links-coming-in",
              "title": "Backlinks for Chapter6_Comprehensive"
            }
          },
          {
            "id": "3f4e79734fa44e42",
            "type": "leaf",
            "state": {
              "type": "outgoing-link",
              "state": {
                "file": "HUST_Academics/Software Engineering/Chapter6_Comprehensive.md",
                "linksCollapsed": false,
                "unlinkedCollapsed": true
              },
              "icon": "links-going-out",
              "title": "Outgoing links from Chapter6_Comprehensive"
            }
          },
          {
            "id": "d41a8be5dc7c4740",
            "type": "leaf",
            "state": {
              "type": "tag",
              "state": {
                "sortOrder": "frequency",
                "useHierarchy": true,
                "showSearch": false,
                "searchQuery": ""
              },
              "icon": "lucide-tags",
              "title": "Tags"
            }
          },
          {
            "id": "3161cce064b9e7c0",
            "type": "leaf",
            "state": {
              "type": "all-properties",
              "state": {
                "sortOrder": "frequency",
                "showSearch": false,
                "searchQuery": ""
              },
              "icon": "lucide-archive",
              "title": "All properties"
            }
          },
          {
            "id": "9ead6eeed3914c34",
            "type": "leaf",
            "state": {
              "type": "outline",
              "state": {
                "file": "HUST_Academics/Software Engineering/Chapter6_Comprehensive.md",
                "followCursor": false,
                "showSearch": false,
                "searchQuery": ""
              },
              "icon": "lucide-list",
              "title": "Outline of Chapter6_Comprehensive"
            }
          },
          {
            "id": "e5e2c08ca8d40b57",
            "type": "leaf",
            "state": {
              "type": "git-view",
              "state": {},
              "icon": "git-pull-request",
              "title": "Source Control"
            }
          }
        ],
        "currentTab": 5
      }
    ],
    "direction": "horizontal",
    "width": 300
  },
  "left-ribbon": {
    "hiddenItems": {
      "obsidian-git:Open Git source control": false,
      "switcher:Open quick switcher": false,
      "graph:Open graph view": false,
      "canvas:Create new canvas": false,
      "daily-notes:Open today's daily note": false,
      "templates:Insert template": false,
      "command-palette:Open command palette": false,
      "bases:Create new base": false
    }
  },
  "active": "4d53f795367e7826",
  "lastOpenFiles": [
    "Self_Academics/Algorithms/Ch09_Medians_and_Order_Statistics.md",
    "Inbox/Archive/418_PDFsam_[Recommended] Introduction to Algorithms.md",
    "Self_Academics/Algorithms/Ch12_Binary_Search_Trees.md",
    "Self_Academics/Algorithms/Ch12_Binary_Search_Trees.md.tmp.32124.46967cf3583a",
    "Inbox/Archive/368_PDFsam_[Recommended] Introduction to Algorithms.md",
    "Self_Academics/Algorithms/Ch11_Hash_Tables.md",
    "Self_Academics/Algorithms/Ch11_Hash_Tables.md.tmp.32124.09d7a97dcf04",
    "Inbox/Archive/344_PDFsam_[Recommended] Introduction to Algorithms.md",
    "Self_Academics/Algorithms/Ch10_Elementary_Data_Structures.md",
    "Self_Academics/Algorithms/Ch10_Elementary_Data_Structures.md.tmp.32124.c03c73dd2b10",
    "Self_Academics/Algorithms/Ch08_Sorting_in_Linear_Time.md",
    "Inbox/Archive/340_PDFsam_[Recommended] Introduction to Algorithms.md",
    "Self_Academics/Algorithms/PartIII_Introduction_Data_Structures.md",
    "Self_Academics/Algorithms/PartIII_Introduction_Data_Structures.md.tmp.32124.5751bb4e8528",
    "Inbox/Archive/312_PDFsam_[Recommended] Introduction to Algorithms.md",
    "Self_Academics/Algorithms/Ch02_Getting_Started.md",
    "Self_Academics/Algorithms/Ch09_Medians_and_Order_Statistics.md.tmp.32124.bac00aeccb69",
    "Inbox/Archive/284_PDFsam_[Recommended] Introduction to Algorithms.md",
    "Self_Academics/Algorithms/Ch08_Sorting_in_Linear_Time.md.tmp.32124.9474bdd63339",
    "Inbox/Archive/255_PDFsam_[Recommended] Introduction to Algorithms.md",
    "Self_Academics/Algorithms/Ch07_Quicksort.md",
    "Self_Academics/Algorithms/Ch07_Quicksort.md.tmp.32124.8a5c3c6800fc",
    "Inbox/Archive/229_PDFsam_[Recommended] Introduction to Algorithms.md",
    "Inbox/Archive/224_PDFsam_[Recommended] Introduction to Algorithms.md",
    "Self_Academics/Algorithms/Ch06_Heapsort.md",
    "Self_Academics/Algorithms/Ch06_Heapsort.md.tmp.32124.4b540439c533",
    "Self_Academics/Algorithms/Ch03_Characterizing_Running_Times.md",
    "Self_Academics/Algorithms/Ch04_Divide_and_Conquer.md",
    "Self_Academics/Algorithms/Ch05_Probabilistic_Analysis_and_Randomized_Algorithms.md",
    "Self_Academics/Algorithms/PartII_Introduction_Sorting_and_Order_Statistics.md",
    "Self_Academics/Algorithms/PartII_Introduction_Sorting_and_Order_Statistics.md.tmp.32124.35355c3449e8",
    "Inbox/Archive/184_PDFsam_[Recommended] Introduction to Algorithms.md",
    "Self_Academics/Algorithms/Ch05_Probabilistic_Analysis_and_Randomized_Algorithms.md.tmp.32124.4a716344c37c",
    "Inbox/Archive/119_PDFsam_[Recommended] Introduction to Algorithms.md",
    "Inbox/Archive/85_PDFsam_[Recommended] Introduction to Algorithms.md",
    "Inbox/Archive/44_PDFsam_[Recommended] Introduction to Algorithms.md",
    "_agent/skills/Untitled.canvas"
  ]
}